[ {
  "name" : "Wall of Wood",
  "names" : null,
  "manaCost" : "{G}",
  "colors" : [ "G" ],
  "colorIdentity" : [ "G" ],
  "type" : "Creature — Wall",
  "supertypes" : null,
  "types" : [ "Creature" ],
  "subtypes" : [ "Wall" ],
  "rarity" : "Common",
  "text" : "Defender (This creature can't attack.)",
  "number" : "309",
  "power" : "0",
  "toughness" : "3",
  "imageUrl" : "http://gatherer.wizards.com/Handlers/Image.ashx?multiverseid=129773&type=card",
  "id" : 2952
}, {
  "name" : "Blanchwood Armor",
  "names" : null,
  "manaCost" : "{2}{G}",
  "colors" : [ "G" ],
  "colorIdentity" : [ "G" ],
  "type" : "Enchantment — Aura",
  "supertypes" : null,
  "types" : [ "Enchantment" ],
  "subtypes" : [ "Aura" ],
  "rarity" : "Uncommon",
  "text" : "Enchant creature\nEnchanted creature gets +1/+1 for each Forest you control.",
  "number" : "253★",
  "power" : null,
  "toughness" : null,
  "imageUrl" : null,
  "id" : 2953
}, {
  "name" : "Forest",
  "names" : null,
  "manaCost" : null,
  "colors" : null,
  "colorIdentity" : [ "G" ],
  "type" : "Basic Land — Forest",
  "supertypes" : [ "Basic" ],
  "types" : [ "Land" ],
  "subtypes" : [ "Forest" ],
  "rarity" : "Common",
  "text" : "({T}: Add {G}.)",
  "number" : "381",
  "power" : null,
  "toughness" : null,
  "imageUrl" : "http://gatherer.wizards.com/Handlers/Image.ashx?multiverseid=129560&type=card",
  "id" : 2954
}, {
  "name" : "Canopy Spider",
  "names" : null,
  "manaCost" : "{1}{G}",
  "colors" : [ "G" ],
  "colorIdentity" : [ "G" ],
  "type" : "Creature — Spider",
  "supertypes" : null,
  "types" : [ "Creature" ],
  "subtypes" : [ "Spider" ],
  "rarity" : "Common",
  "text" : "Reach (This creature can block creatures with flying.)",
  "number" : "254",
  "power" : "1",
  "toughness" : "3",
  "imageUrl" : "http://gatherer.wizards.com/Handlers/Image.ashx?multiverseid=135185&type=card",
  "id" : 2955
}, {
  "name" : "Rhox",
  "names" : null,
  "manaCost" : "{4}{G}{G}",
  "colors" : [ "G" ],
  "colorIdentity" : [ "G" ],
  "type" : "Creature — Rhino Beast",
  "supertypes" : null,
  "types" : [ "Creature" ],
  "subtypes" : [ "Rhino", "Beast" ],
  "rarity" : "Rare",
  "text" : "You may have Rhox assign its combat damage as though it weren't blocked.\n{2}{G}: Regenerate Rhox. (The next time this creature would be destroyed this turn, it isn't. Instead tap it, remove all damage from it, and remove it from combat.)",
  "number" : "291",
  "power" : "5",
  "toughness" : "5",
  "imageUrl" : "http://gatherer.wizards.com/Handlers/Image.ashx?multiverseid=106504&type=card",
  "id" : 2956
}, {
  "name" : "Grizzly Bears",
  "names" : null,
  "manaCost" : "{1}{G}",
  "colors" : [ "G" ],
  "colorIdentity" : [ "G" ],
  "type" : "Creature — Bear",
  "supertypes" : null,
  "types" : [ "Creature" ],
  "subtypes" : [ "Bear" ],
  "rarity" : "Common",
  "text" : null,
  "number" : "268",
  "power" : "2",
  "toughness" : "2",
  "imageUrl" : "http://gatherer.wizards.com/Handlers/Image.ashx?multiverseid=129586&type=card",
  "id" : 2957
}, {
  "name" : "Quirion Dryad",
  "names" : null,
  "manaCost" : "{1}{G}",
  "colors" : [ "G" ],
  "colorIdentity" : [ "G" ],
  "type" : "Creature — Dryad",
  "supertypes" : null,
  "types" : [ "Creature" ],
  "subtypes" : [ "Dryad" ],
  "rarity" : "Rare",
  "text" : "Whenever you cast a spell that's white, blue, black, or red, put a +1/+1 counter on Quirion Dryad.",
  "number" : "287",
  "power" : "1",
  "toughness" : "1",
  "imageUrl" : "http://gatherer.wizards.com/Handlers/Image.ashx?multiverseid=130489&type=card",
  "id" : 2958
}, {
  "name" : "Stalking Tiger",
  "names" : null,
  "manaCost" : "{3}{G}",
  "colors" : [ "G" ],
  "colorIdentity" : [ "G" ],
  "type" : "Creature — Cat",
  "supertypes" : null,
  "types" : [ "Creature" ],
  "subtypes" : [ "Cat" ],
  "rarity" : "Common",
  "text" : "Stalking Tiger can't be blocked by more than one creature.",
  "number" : "299",
  "power" : "3",
  "toughness" : "3",
  "imageUrl" : "http://gatherer.wizards.com/Handlers/Image.ashx?multiverseid=135184&type=card",
  "id" : 2959
}, {
  "name" : "Aspect of Wolf",
  "names" : null,
  "manaCost" : "{1}{G}",
  "colors" : [ "G" ],
  "colorIdentity" : [ "G" ],
  "type" : "Enchantment — Aura",
  "supertypes" : null,
  "types" : [ "Enchantment" ],
  "subtypes" : [ "Aura" ],
  "rarity" : "Rare",
  "text" : "Enchant creature\nEnchanted creature gets +X/+Y, where X is half the number of Forests you control, rounded down, and Y is half the number of Forests you control, rounded up.",
  "number" : "185",
  "power" : null,
  "toughness" : null,
  "imageUrl" : "http://gatherer.wizards.com/Handlers/Image.ashx?multiverseid=737&type=card",
  "id" : 2960
}, {
  "name" : "Upwelling",
  "names" : null,
  "manaCost" : "{3}{G}",
  "colors" : [ "G" ],
  "colorIdentity" : [ "G" ],
  "type" : "Enchantment",
  "supertypes" : null,
  "types" : [ "Enchantment" ],
  "subtypes" : null,
  "rarity" : "Rare",
  "text" : "Players don't lose unspent mana as steps and phases end.",
  "number" : "306★",
  "power" : null,
  "toughness" : null,
  "imageUrl" : null,
  "id" : 2961
}, {
  "name" : "Brushland",
  "names" : null,
  "manaCost" : null,
  "colors" : null,
  "colorIdentity" : [ "G", "W" ],
  "type" : "Land",
  "supertypes" : null,
  "types" : [ "Land" ],
  "subtypes" : null,
  "rarity" : "Rare",
  "text" : "{T}: Add {C}.\n{T}: Add {G} or {W}. Brushland deals 1 damage to you.",
  "number" : "349",
  "power" : null,
  "toughness" : null,
  "imageUrl" : "http://gatherer.wizards.com/Handlers/Image.ashx?multiverseid=129496&type=card",
  "id" : 2962
}, {
  "name" : "Aggressive Urge",
  "names" : null,
  "manaCost" : "{1}{G}",
  "colors" : [ "G" ],
  "colorIdentity" : [ "G" ],
  "type" : "Instant",
  "supertypes" : null,
  "types" : [ "Instant" ],
  "subtypes" : null,
  "rarity" : "Common",
  "text" : "Target creature gets +1/+1 until end of turn.\nDraw a card.",
  "number" : "250",
  "power" : null,
  "toughness" : null,
  "imageUrl" : "http://gatherer.wizards.com/Handlers/Image.ashx?multiverseid=130525&type=card",
  "id" : 2963
}, {
  "name" : "Upwelling",
  "names" : null,
  "manaCost" : "{3}{G}",
  "colors" : [ "G" ],
  "colorIdentity" : [ "G" ],
  "type" : "Enchantment",
  "supertypes" : null,
  "types" : [ "Enchantment" ],
  "subtypes" : null,
  "rarity" : "Rare",
  "text" : "Players don't lose unspent mana as steps and phases end.",
  "number" : "306",
  "power" : null,
  "toughness" : null,
  "imageUrl" : "http://gatherer.wizards.com/Handlers/Image.ashx?multiverseid=130494&type=card",
  "id" : 2964
}, {
  "name" : "Recollect",
  "names" : null,
  "manaCost" : "{2}{G}",
  "colors" : [ "G" ],
  "colorIdentity" : [ "G" ],
  "type" : "Sorcery",
  "supertypes" : null,
  "types" : [ "Sorcery" ],
  "subtypes" : null,
  "rarity" : "Uncommon",
  "text" : "Return target card from your graveyard to your hand.",
  "number" : "289",
  "power" : null,
  "toughness" : null,
  "imageUrl" : "http://gatherer.wizards.com/Handlers/Image.ashx?multiverseid=130507&type=card",
  "id" : 2965
}, {
  "name" : "Sylvan Scrying",
  "names" : null,
  "manaCost" : "{1}{G}",
  "colors" : [ "G" ],
  "colorIdentity" : [ "G" ],
  "type" : "Sorcery",
  "supertypes" : null,
  "types" : [ "Sorcery" ],
  "subtypes" : null,
  "rarity" : "Uncommon",
  "text" : "Search your library for a land card, reveal it, put it into your hand, then shuffle.",
  "number" : "302",
  "power" : null,
  "toughness" : null,
  "imageUrl" : "http://gatherer.wizards.com/Handlers/Image.ashx?multiverseid=130513&type=card",
  "id" : 2966
}, {
  "name" : "Treetop Bracers",
  "names" : null,
  "manaCost" : "{1}{G}",
  "colors" : [ "G" ],
  "colorIdentity" : [ "G" ],
  "type" : "Enchantment — Aura",
  "supertypes" : null,
  "types" : [ "Enchantment" ],
  "subtypes" : [ "Aura" ],
  "rarity" : "Common",
  "text" : "Enchant creature (Target a creature as you cast this. This card enters the battlefield attached to that creature.)\nEnchanted creature gets +1/+1 and can't be blocked except by creatures with flying.",
  "number" : "304",
  "power" : null,
  "toughness" : null,
  "imageUrl" : "http://gatherer.wizards.com/Handlers/Image.ashx?multiverseid=129777&type=card",
  "id" : 2967
}, {
  "name" : "Elvish Champion",
  "names" : null,
  "manaCost" : "{1}{G}{G}",
  "colors" : [ "G" ],
  "colorIdentity" : [ "G" ],
  "type" : "Creature — Elf",
  "supertypes" : null,
  "types" : [ "Creature" ],
  "subtypes" : [ "Elf" ],
  "rarity" : "Rare",
  "text" : "Other Elf creatures get +1/+1 and have forestwalk. (They can't be blocked as long as defending player controls a Forest.)",
  "number" : "261★",
  "power" : "2",
  "toughness" : "2",
  "imageUrl" : null,
  "id" : 2968
}, {
  "name" : "Might Weaver",
  "names" : null,
  "manaCost" : "{1}{G}",
  "colors" : [ "G" ],
  "colorIdentity" : [ "G" ],
  "type" : "Creature — Human Wizard",
  "supertypes" : null,
  "types" : [ "Creature" ],
  "subtypes" : [ "Human", "Wizard" ],
  "rarity" : "Uncommon",
  "text" : "{2}: Target red or white creature gains trample until end of turn. (It can deal excess combat damage to the player or planeswalker it's attacking.)",
  "number" : "278",
  "power" : "2",
  "toughness" : "1",
  "imageUrl" : "http://gatherer.wizards.com/Handlers/Image.ashx?multiverseid=130996&type=card",
  "id" : 2969
}, {
  "name" : "Pincher Beetles",
  "names" : null,
  "manaCost" : "{2}{G}",
  "colors" : [ "G" ],
  "colorIdentity" : [ "G" ],
  "type" : "Creature — Insect",
  "supertypes" : null,
  "types" : [ "Creature" ],
  "subtypes" : [ "Insect" ],
  "rarity" : "Common",
  "text" : "Shroud (This creature can't be the target of spells or abilities.)",
  "number" : "285★",
  "power" : "3",
  "toughness" : "1",
  "imageUrl" : null,
  "id" : 2970
}, {
  "name" : "Joiner Adept",
  "names" : null,
  "manaCost" : "{1}{G}",
  "colors" : [ "G" ],
  "colorIdentity" : [ "G" ],
  "type" : "Creature — Elf Druid",
  "supertypes" : null,
  "types" : [ "Creature" ],
  "subtypes" : [ "Elf", "Druid" ],
  "rarity" : "Rare",
  "text" : "Lands you control have \"{T}: Add one mana of any color.\"",
  "number" : "271",
  "power" : "2",
  "toughness" : "1",
  "imageUrl" : "http://gatherer.wizards.com/Handlers/Image.ashx?multiverseid=130500&type=card",
  "id" : 2971
}, {
  "name" : "Viridian Shaman",
  "names" : null,
  "manaCost" : "{2}{G}",
  "colors" : [ "G" ],
  "colorIdentity" : [ "G" ],
  "type" : "Creature — Elf Shaman",
  "supertypes" : null,
  "types" : [ "Creature" ],
  "subtypes" : [ "Elf", "Shaman" ],
  "rarity" : "Uncommon",
  "text" : "When Viridian Shaman enters the battlefield, destroy target artifact.",
  "number" : "308",
  "power" : "2",
  "toughness" : "2",
  "imageUrl" : "http://gatherer.wizards.com/Handlers/Image.ashx?multiverseid=129792&type=card",
  "id" : 2972
}, {
  "name" : "Elvish Berserker",
  "names" : null,
  "manaCost" : "{G}",
  "colors" : [ "G" ],
  "colorIdentity" : [ "G" ],
  "type" : "Creature — Elf Berserker",
  "supertypes" : null,
  "types" : [ "Creature" ],
  "subtypes" : [ "Elf", "Berserker" ],
  "rarity" : "Common",
  "text" : "Whenever Elvish Berserker becomes blocked, it gets +1/+1 until end of turn for each creature blocking it.",
  "number" : "260",
  "power" : "1",
  "toughness" : "1",
  "imageUrl" : "http://gatherer.wizards.com/Handlers/Image.ashx?multiverseid=129533&type=card",
  "id" : 2973
}, {
  "name" : "Rampant Growth",
  "names" : null,
  "manaCost" : "{1}{G}",
  "colors" : [ "G" ],
  "colorIdentity" : [ "G" ],
  "type" : "Sorcery",
  "supertypes" : null,
  "types" : [ "Sorcery" ],
  "subtypes" : null,
  "rarity" : "Common",
  "text" : "Search your library for a basic land card, put that card onto the battlefield tapped, then shuffle.",
  "number" : "288",
  "power" : null,
  "toughness" : null,
  "imageUrl" : "http://gatherer.wizards.com/Handlers/Image.ashx?multiverseid=129690&type=card",
  "id" : 2974
}, {
  "name" : "Stampeding Wildebeests",
  "names" : null,
  "manaCost" : "{2}{G}{G}",
  "colors" : [ "G" ],
  "colorIdentity" : [ "G" ],
  "type" : "Creature — Antelope Beast",
  "supertypes" : null,
  "types" : [ "Creature" ],
  "subtypes" : [ "Antelope", "Beast" ],
  "rarity" : "Uncommon",
  "text" : "Trample (This creature can deal excess combat damage to the player or planeswalker it's attacking.)\nAt the beginning of your upkeep, return a green creature you control to its owner's hand.",
  "number" : "300",
  "power" : "5",
  "toughness" : "4",
  "imageUrl" : "http://gatherer.wizards.com/Handlers/Image.ashx?multiverseid=135264&type=card",
  "id" : 2975
}, {
  "name" : "Natural Spring",
  "names" : null,
  "manaCost" : "{3}{G}{G}",
  "colors" : [ "G" ],
  "colorIdentity" : [ "G" ],
  "type" : "Sorcery",
  "supertypes" : null,
  "types" : [ "Sorcery" ],
  "subtypes" : null,
  "rarity" : "Common",
  "text" : "Target player gains 8 life.",
  "number" : "281",
  "power" : null,
  "toughness" : null,
  "imageUrl" : "http://gatherer.wizards.com/Handlers/Image.ashx?multiverseid=129655&type=card",
  "id" : 2976
}, {
  "name" : "Karplusan Forest",
  "names" : null,
  "manaCost" : null,
  "colors" : null,
  "colorIdentity" : [ "G", "R" ],
  "type" : "Land",
  "supertypes" : null,
  "types" : [ "Land" ],
  "subtypes" : null,
  "rarity" : "Rare",
  "text" : "{T}: Add {C}.\n{T}: Add {R} or {G}. Karplusan Forest deals 1 damage to you.",
  "number" : "354",
  "power" : null,
  "toughness" : null,
  "imageUrl" : "http://gatherer.wizards.com/Handlers/Image.ashx?multiverseid=129614&type=card",
  "id" : 2977
}, {
  "name" : "Verdant Force",
  "names" : null,
  "manaCost" : "{5}{G}{G}{G}",
  "colors" : [ "G" ],
  "colorIdentity" : [ "G" ],
  "type" : "Creature — Elemental",
  "supertypes" : null,
  "types" : [ "Creature" ],
  "subtypes" : [ "Elemental" ],
  "rarity" : "Rare",
  "text" : "At the beginning of each upkeep, create a 1/1 green Saproling creature token.",
  "number" : "307",
  "power" : "7",
  "toughness" : "7",
  "imageUrl" : "http://gatherer.wizards.com/Handlers/Image.ashx?multiverseid=129788&type=card",
  "id" : 2978
}, {
  "name" : "Rushwood Dryad",
  "names" : null,
  "manaCost" : "{1}{G}",
  "colors" : [ "G" ],
  "colorIdentity" : [ "G" ],
  "type" : "Creature — Dryad",
  "supertypes" : null,
  "types" : [ "Creature" ],
  "subtypes" : [ "Dryad" ],
  "rarity" : "Common",
  "text" : "Forestwalk (This creature can't be blocked as long as defending player controls a Forest.)",
  "number" : "294★",
  "power" : "2",
  "toughness" : "1",
  "imageUrl" : null,
  "id" : 2979
}, {
  "name" : "Rootwalla",
  "names" : null,
  "manaCost" : "{2}{G}",
  "colors" : [ "G" ],
  "colorIdentity" : [ "G" ],
  "type" : "Creature — Lizard",
  "supertypes" : null,
  "types" : [ "Creature" ],
  "subtypes" : [ "Lizard" ],
  "rarity" : "Common",
  "text" : "{1}{G}: Rootwalla gets +2/+2 until end of turn. Activate only once each turn.",
  "number" : "293",
  "power" : "2",
  "toughness" : "2",
  "imageUrl" : "http://gatherer.wizards.com/Handlers/Image.ashx?multiverseid=129707&type=card",
  "id" : 2980
}, {
  "name" : "Karplusan Strider",
  "names" : null,
  "manaCost" : "{3}{G}",
  "colors" : [ "G" ],
  "colorIdentity" : [ "G" ],
  "type" : "Creature — Yeti",
  "supertypes" : null,
  "types" : [ "Creature" ],
  "subtypes" : [ "Yeti" ],
  "rarity" : "Uncommon",
  "text" : "Karplusan Strider can't be the target of blue or black spells.",
  "number" : "272",
  "power" : "3",
  "toughness" : "4",
  "imageUrl" : "http://gatherer.wizards.com/Handlers/Image.ashx?multiverseid=129911&type=card",
  "id" : 2981
}, {
  "name" : "Tangle Spider",
  "names" : null,
  "manaCost" : "{4}{G}{G}",
  "colors" : [ "G" ],
  "colorIdentity" : [ "G" ],
  "type" : "Creature — Spider",
  "supertypes" : null,
  "types" : [ "Creature" ],
  "subtypes" : [ "Spider" ],
  "rarity" : "Uncommon",
  "text" : "Flash (You may cast this spell any time you could cast an instant.)\nReach (This creature can block creatures with flying.)",
  "number" : "303★",
  "power" : "3",
  "toughness" : "4",
  "imageUrl" : null,
  "id" : 2982
}, {
  "name" : "Root Maze",
  "names" : null,
  "manaCost" : "{G}",
  "colors" : [ "G" ],
  "colorIdentity" : [ "G" ],
  "type" : "Enchantment",
  "supertypes" : null,
  "types" : [ "Enchantment" ],
  "subtypes" : null,
  "rarity" : "Rare",
  "text" : "Artifacts and lands enter the battlefield tapped.",
  "number" : "292",
  "power" : null,
  "toughness" : null,
  "imageUrl" : "http://gatherer.wizards.com/Handlers/Image.ashx?multiverseid=135251&type=card",
  "id" : 2983
}, {
  "name" : "Creeping Mold",
  "names" : null,
  "manaCost" : "{2}{G}{G}",
  "colors" : [ "G" ],
  "colorIdentity" : [ "G" ],
  "type" : "Sorcery",
  "supertypes" : null,
  "types" : [ "Sorcery" ],
  "subtypes" : null,
  "rarity" : "Uncommon",
  "text" : "Destroy target artifact, enchantment, or land.",
  "number" : "258",
  "power" : null,
  "toughness" : null,
  "imageUrl" : "http://gatherer.wizards.com/Handlers/Image.ashx?multiverseid=129512&type=card",
  "id" : 2984
}, {
  "name" : "Avatar of Might",
  "names" : null,
  "manaCost" : "{6}{G}{G}",
  "colors" : [ "G" ],
  "colorIdentity" : [ "G" ],
  "type" : "Creature — Avatar",
  "supertypes" : null,
  "types" : [ "Creature" ],
  "subtypes" : [ "Avatar" ],
  "rarity" : "Rare",
  "text" : "If an opponent controls at least four more creatures than you, this spell costs {6} less to cast.\nTrample (This creature can deal excess combat damage to the player or planeswalker it's attacking.)",
  "number" : "251",
  "power" : "8",
  "toughness" : "8",
  "imageUrl" : "http://gatherer.wizards.com/Handlers/Image.ashx?multiverseid=135249&type=card",
  "id" : 2985
}, {
  "name" : "Overgrowth",
  "names" : null,
  "manaCost" : "{2}{G}",
  "colors" : [ "G" ],
  "colorIdentity" : [ "G" ],
  "type" : "Enchantment — Aura",
  "supertypes" : null,
  "types" : [ "Enchantment" ],
  "subtypes" : [ "Aura" ],
  "rarity" : "Common",
  "text" : "Enchant land\nWhenever enchanted land is tapped for mana, its controller adds an additional {G}{G}.",
  "number" : "283★",
  "power" : null,
  "toughness" : null,
  "imageUrl" : null,
  "id" : 2986
}, {
  "name" : "Primal Rage",
  "names" : null,
  "manaCost" : "{1}{G}",
  "colors" : [ "G" ],
  "colorIdentity" : [ "G" ],
  "type" : "Enchantment",
  "supertypes" : null,
  "types" : [ "Enchantment" ],
  "subtypes" : null,
  "rarity" : "Uncommon",
  "text" : "Creatures you control have trample. (A creature with trample can deal excess combat damage to the player or planeswalker it's attacking.)",
  "number" : "286",
  "power" : null,
  "toughness" : null,
  "imageUrl" : "http://gatherer.wizards.com/Handlers/Image.ashx?multiverseid=136288&type=card",
  "id" : 2987
}, {
  "name" : "Molimo, Maro-Sorcerer",
  "names" : null,
  "manaCost" : "{4}{G}{G}{G}",
  "colors" : [ "G" ],
  "colorIdentity" : [ "G" ],
  "type" : "Legendary Creature — Elemental",
  "supertypes" : [ "Legendary" ],
  "types" : [ "Creature" ],
  "subtypes" : [ "Elemental" ],
  "rarity" : "Rare",
  "text" : "Trample (This creature can deal excess combat damage to the player or planeswalker it's attacking.)\nMolimo, Maro-Sorcerer's power and toughness are each equal to the number of lands you control.",
  "number" : "280",
  "power" : "*",
  "toughness" : "*",
  "imageUrl" : "http://gatherer.wizards.com/Handlers/Image.ashx?multiverseid=106368&type=card",
  "id" : 2988
}, {
  "name" : "Forest",
  "names" : null,
  "manaCost" : null,
  "colors" : null,
  "colorIdentity" : [ "G" ],
  "type" : "Basic Land — Forest",
  "supertypes" : [ "Basic" ],
  "types" : [ "Land" ],
  "subtypes" : [ "Forest" ],
  "rarity" : "Common",
  "text" : "({T}: Add {G}.)",
  "number" : "382",
  "power" : null,
  "toughness" : null,
  "imageUrl" : "http://gatherer.wizards.com/Handlers/Image.ashx?multiverseid=129561&type=card",
  "id" : 2989
}, {
  "name" : "Composite Golem",
  "names" : null,
  "manaCost" : "{6}",
  "colors" : null,
  "colorIdentity" : [ "B", "G", "R", "U", "W" ],
  "type" : "Artifact Creature — Golem",
  "supertypes" : null,
  "types" : [ "Artifact", "Creature" ],
  "subtypes" : [ "Golem" ],
  "rarity" : "Uncommon",
  "text" : "Sacrifice Composite Golem: Add {W}{U}{B}{R}{G}.",
  "number" : "318",
  "power" : "4",
  "toughness" : "4",
  "imageUrl" : "http://gatherer.wizards.com/Handlers/Image.ashx?multiverseid=135275&type=card",
  "id" : 2990
}, {
  "name" : "Llanowar Sentinel",
  "names" : null,
  "manaCost" : "{2}{G}",
  "colors" : [ "G" ],
  "colorIdentity" : [ "G" ],
  "type" : "Creature — Elf",
  "supertypes" : null,
  "types" : [ "Creature" ],
  "subtypes" : [ "Elf" ],
  "rarity" : "Common",
  "text" : "When Llanowar Sentinel enters the battlefield, you may pay {1}{G}. If you do, search your library for a card named Llanowar Sentinel, put that card onto the battlefield, then shuffle.",
  "number" : "275",
  "power" : "2",
  "toughness" : "3",
  "imageUrl" : "http://gatherer.wizards.com/Handlers/Image.ashx?multiverseid=129536&type=card",
  "id" : 2991
}, {
  "name" : "Hurricane",
  "names" : null,
  "manaCost" : "{X}{G}",
  "colors" : [ "G" ],
  "colorIdentity" : [ "G" ],
  "type" : "Sorcery",
  "supertypes" : null,
  "types" : [ "Sorcery" ],
  "subtypes" : null,
  "rarity" : "Rare",
  "text" : "Hurricane deals X damage to each creature with flying and each player.",
  "number" : "270",
  "power" : null,
  "toughness" : null,
  "imageUrl" : "http://gatherer.wizards.com/Handlers/Image.ashx?multiverseid=129885&type=card",
  "id" : 2992
}, {
  "name" : "Skyshroud Ranger",
  "names" : null,
  "manaCost" : "{G}",
  "colors" : [ "G" ],
  "colorIdentity" : [ "G" ],
  "type" : "Creature — Elf Ranger",
  "supertypes" : null,
  "types" : [ "Creature" ],
  "subtypes" : [ "Elf", "Ranger" ],
  "rarity" : "Common",
  "text" : "{T}: You may put a land card from your hand onto the battlefield. Activate only as a sorcery.",
  "number" : "297",
  "power" : "1",
  "toughness" : "1",
  "imageUrl" : "http://gatherer.wizards.com/Handlers/Image.ashx?multiverseid=135182&type=card",
  "id" : 2993
}, {
  "name" : "Regeneration",
  "names" : null,
  "manaCost" : "{1}{G}",
  "colors" : [ "G" ],
  "colorIdentity" : [ "G" ],
  "type" : "Enchantment — Aura",
  "supertypes" : null,
  "types" : [ "Enchantment" ],
  "subtypes" : [ "Aura" ],
  "rarity" : "Uncommon",
  "text" : "Enchant creature (Target a creature as you cast this. This card enters the battlefield attached to that creature.)\n{G}: Regenerate enchanted creature. (The next time that creature would be destroyed this turn, it isn't. Instead tap it, remove all damage from it, and remove it from combat.)",
  "number" : "290",
  "power" : null,
  "toughness" : null,
  "imageUrl" : "http://gatherer.wizards.com/Handlers/Image.ashx?multiverseid=129696&type=card",
  "id" : 2994
}, {
  "name" : "Tangle Spider",
  "names" : null,
  "manaCost" : "{4}{G}{G}",
  "colors" : [ "G" ],
  "colorIdentity" : [ "G" ],
  "type" : "Creature — Spider",
  "supertypes" : null,
  "types" : [ "Creature" ],
  "subtypes" : [ "Spider" ],
  "rarity" : "Uncommon",
  "text" : "Flash (You may cast this spell any time you could cast an instant.)\nReach (This creature can block creatures with flying.)",
  "number" : "303",
  "power" : "3",
  "toughness" : "4",
  "imageUrl" : "http://gatherer.wizards.com/Handlers/Image.ashx?multiverseid=135231&type=card",
  "id" : 2995
}, {
  "name" : "Birds of Paradise",
  "names" : null,
  "manaCost" : "{G}",
  "colors" : [ "G" ],
  "colorIdentity" : [ "G" ],
  "type" : "Creature — Bird",
  "supertypes" : null,
  "types" : [ "Creature" ],
  "subtypes" : [ "Bird" ],
  "rarity" : "Rare",
  "text" : "Flying\n{T}: Add one mana of any color.",
  "number" : "187",
  "power" : "0",
  "toughness" : "1",
  "imageUrl" : "http://gatherer.wizards.com/Handlers/Image.ashx?multiverseid=739&type=card",
  "id" : 2996
}, {
  "name" : "Birds of Paradise",
  "names" : null,
  "manaCost" : "{G}",
  "colors" : [ "G" ],
  "colorIdentity" : [ "G" ],
  "type" : "Creature — Bird",
  "supertypes" : null,
  "types" : [ "Creature" ],
  "subtypes" : [ "Bird" ],
  "rarity" : "Rare",
  "text" : "Flying\n{T}: Add one mana of any color.",
  "number" : "252★",
  "power" : "0",
  "toughness" : "1",
  "imageUrl" : null,
  "id" : 2997
}, {
  "name" : "Stampeding Wildebeests",
  "names" : null,
  "manaCost" : "{2}{G}{G}",
  "colors" : [ "G" ],
  "colorIdentity" : [ "G" ],
  "type" : "Creature — Antelope Beast",
  "supertypes" : null,
  "types" : [ "Creature" ],
  "subtypes" : [ "Antelope", "Beast" ],
  "rarity" : "Uncommon",
  "text" : "Trample (This creature can deal excess combat damage to the player or planeswalker it's attacking.)\nAt the beginning of your upkeep, return a green creature you control to its owner's hand.",
  "number" : "300★",
  "power" : "5",
  "toughness" : "4",
  "imageUrl" : null,
  "id" : 2998
}, {
  "name" : "Canopy Spider",
  "names" : null,
  "manaCost" : "{1}{G}",
  "colors" : [ "G" ],
  "colorIdentity" : [ "G" ],
  "type" : "Creature — Spider",
  "supertypes" : null,
  "types" : [ "Creature" ],
  "subtypes" : [ "Spider" ],
  "rarity" : "Common",
  "text" : "Reach (This creature can block creatures with flying.)",
  "number" : "254★",
  "power" : "1",
  "toughness" : "3",
  "imageUrl" : null,
  "id" : 2999
}, {
  "name" : "Regeneration",
  "names" : null,
  "manaCost" : "{1}{G}",
  "colors" : [ "G" ],
  "colorIdentity" : [ "G" ],
  "type" : "Enchantment — Aura",
  "supertypes" : null,
  "types" : [ "Enchantment" ],
  "subtypes" : [ "Aura" ],
  "rarity" : "Uncommon",
  "text" : "Enchant creature (Target a creature as you cast this. This card enters the battlefield attached to that creature.)\n{G}: Regenerate enchanted creature. (The next time that creature would be destroyed this turn, it isn't. Instead tap it, remove all damage from it, and remove it from combat.)",
  "number" : "290★",
  "power" : null,
  "toughness" : null,
  "imageUrl" : null,
  "id" : 3000
}, {
  "name" : "Molimo, Maro-Sorcerer",
  "names" : null,
  "manaCost" : "{4}{G}{G}{G}",
  "colors" : [ "G" ],
  "colorIdentity" : [ "G" ],
  "type" : "Legendary Creature — Elemental",
  "supertypes" : [ "Legendary" ],
  "types" : [ "Creature" ],
  "subtypes" : [ "Elemental" ],
  "rarity" : "Rare",
  "text" : "Trample (This creature can deal excess combat damage to the player or planeswalker it's attacking.)\nMolimo, Maro-Sorcerer's power and toughness are each equal to the number of lands you control.",
  "number" : "280★",
  "power" : "*",
  "toughness" : "*",
  "imageUrl" : null,
  "id" : 3001
}, {
  "name" : "Blanchwood Armor",
  "names" : null,
  "manaCost" : "{2}{G}",
  "colors" : [ "G" ],
  "colorIdentity" : [ "G" ],
  "type" : "Enchantment — Aura",
  "supertypes" : null,
  "types" : [ "Enchantment" ],
  "subtypes" : [ "Aura" ],
  "rarity" : "Uncommon",
  "text" : "Enchant creature\nEnchanted creature gets +1/+1 for each Forest you control.",
  "number" : "253",
  "power" : null,
  "toughness" : null,
  "imageUrl" : "http://gatherer.wizards.com/Handlers/Image.ashx?multiverseid=135267&type=card",
  "id" : 3002
}, {
  "name" : "Elven Riders",
  "names" : null,
  "manaCost" : "{3}{G}{G}",
  "colors" : [ "G" ],
  "colorIdentity" : [ "G" ],
  "type" : "Creature — Elf",
  "supertypes" : null,
  "types" : [ "Creature" ],
  "subtypes" : [ "Elf" ],
  "rarity" : "Uncommon",
  "text" : "Elven Riders can't be blocked except by Walls and/or creatures with flying.",
  "number" : "259",
  "power" : "3",
  "toughness" : "3",
  "imageUrl" : "http://gatherer.wizards.com/Handlers/Image.ashx?multiverseid=135266&type=card",
  "id" : 3003
}, {
  "name" : "Yavimaya Enchantress",
  "names" : null,
  "manaCost" : "{2}{G}",
  "colors" : [ "G" ],
  "colorIdentity" : [ "G" ],
  "type" : "Creature — Human Druid",
  "supertypes" : null,
  "types" : [ "Creature" ],
  "subtypes" : [ "Human", "Druid" ],
  "rarity" : "Uncommon",
  "text" : "Yavimaya Enchantress gets +1/+1 for each enchantment on the battlefield.",
  "number" : "310",
  "power" : "2",
  "toughness" : "2",
  "imageUrl" : "http://gatherer.wizards.com/Handlers/Image.ashx?multiverseid=130515&type=card",
  "id" : 3004
}, {
  "name" : "Mirri, Cat Warrior",
  "names" : null,
  "manaCost" : "{1}{G}{G}",
  "colors" : [ "G" ],
  "colorIdentity" : [ "G" ],
  "type" : "Legendary Creature — Cat Warrior",
  "supertypes" : [ "Legendary" ],
  "types" : [ "Creature" ],
  "subtypes" : [ "Cat", "Warrior" ],
  "rarity" : "Rare",
  "text" : "First strike, forestwalk, vigilance (This creature deals combat damage before creatures without first strike, it can't be blocked as long as defending player controls a Forest, and attacking doesn't cause this creature to tap.)",
  "number" : "279",
  "power" : "2",
  "toughness" : "3",
  "imageUrl" : "http://gatherer.wizards.com/Handlers/Image.ashx?multiverseid=106405&type=card",
  "id" : 3005
}, {
  "name" : "Overrun",
  "names" : null,
  "manaCost" : "{2}{G}{G}{G}",
  "colors" : [ "G" ],
  "colorIdentity" : [ "G" ],
  "type" : "Sorcery",
  "supertypes" : null,
  "types" : [ "Sorcery" ],
  "subtypes" : null,
  "rarity" : "Uncommon",
  "text" : "Creatures you control get +3/+3 and gain trample until end of turn.",
  "number" : "284",
  "power" : null,
  "toughness" : null,
  "imageUrl" : "http://gatherer.wizards.com/Handlers/Image.ashx?multiverseid=130506&type=card",
  "id" : 3006
}, {
  "name" : "Lure",
  "names" : null,
  "manaCost" : "{1}{G}{G}",
  "colors" : [ "G" ],
  "colorIdentity" : [ "G" ],
  "type" : "Enchantment — Aura",
  "supertypes" : null,
  "types" : [ "Enchantment" ],
  "subtypes" : [ "Aura" ],
  "rarity" : "Uncommon",
  "text" : "Enchant creature\nAll creatures able to block enchanted creature do so.",
  "number" : "276★",
  "power" : null,
  "toughness" : null,
  "imageUrl" : null,
  "id" : 3007
}, {
  "name" : "Sylvan Basilisk",
  "names" : null,
  "manaCost" : "{3}{G}{G}",
  "colors" : [ "G" ],
  "colorIdentity" : [ "G" ],
  "type" : "Creature — Basilisk",
  "supertypes" : null,
  "types" : [ "Creature" ],
  "subtypes" : [ "Basilisk" ],
  "rarity" : "Uncommon",
  "text" : "Whenever Sylvan Basilisk becomes blocked by a creature, destroy that creature.",
  "number" : "301",
  "power" : "2",
  "toughness" : "4",
  "imageUrl" : "http://gatherer.wizards.com/Handlers/Image.ashx?multiverseid=135215&type=card",
  "id" : 3008
}, {
  "name" : "Giant Growth",
  "names" : null,
  "manaCost" : "{G}",
  "colors" : [ "G" ],
  "colorIdentity" : [ "G" ],
  "type" : "Instant",
  "supertypes" : null,
  "types" : [ "Instant" ],
  "subtypes" : null,
  "rarity" : "Common",
  "text" : "Target creature gets +3/+3 until end of turn.",
  "number" : "266",
  "power" : null,
  "toughness" : null,
  "imageUrl" : "http://gatherer.wizards.com/Handlers/Image.ashx?multiverseid=129568&type=card",
  "id" : 3009
}, {
  "name" : "Llanowar Elves",
  "names" : null,
  "manaCost" : "{G}",
  "colors" : [ "G" ],
  "colorIdentity" : [ "G" ],
  "type" : "Creature — Elf Druid",
  "supertypes" : null,
  "types" : [ "Creature" ],
  "subtypes" : [ "Elf", "Druid" ],
  "rarity" : "Common",
  "text" : "{T}: Add {G}.",
  "number" : "274",
  "power" : "1",
  "toughness" : "1",
  "imageUrl" : "http://gatherer.wizards.com/Handlers/Image.ashx?multiverseid=129626&type=card",
  "id" : 3010
}, {
  "name" : "Primal Rage",
  "names" : null,
  "manaCost" : "{1}{G}",
  "colors" : [ "G" ],
  "colorIdentity" : [ "G" ],
  "type" : "Enchantment",
  "supertypes" : null,
  "types" : [ "Enchantment" ],
  "subtypes" : null,
  "rarity" : "Uncommon",
  "text" : "Creatures you control have trample. (A creature with trample can deal excess combat damage to the player or planeswalker it's attacking.)",
  "number" : "286★",
  "power" : null,
  "toughness" : null,
  "imageUrl" : null,
  "id" : 3011
}, {
  "name" : "Forest",
  "names" : null,
  "manaCost" : null,
  "colors" : null,
  "colorIdentity" : [ "G" ],
  "type" : "Basic Land — Forest",
  "supertypes" : [ "Basic" ],
  "types" : [ "Land" ],
  "subtypes" : [ "Forest" ],
  "rarity" : "Common",
  "text" : "({T}: Add {G}.)",
  "number" : "383",
  "power" : null,
  "toughness" : null,
  "imageUrl" : "http://gatherer.wizards.com/Handlers/Image.ashx?multiverseid=129562&type=card",
  "id" : 3012
}, {
  "name" : "Pincher Beetles",
  "names" : null,
  "manaCost" : "{2}{G}",
  "colors" : [ "G" ],
  "colorIdentity" : [ "G" ],
  "type" : "Creature — Insect",
  "supertypes" : null,
  "types" : [ "Creature" ],
  "subtypes" : [ "Insect" ],
  "rarity" : "Common",
  "text" : "Shroud (This creature can't be the target of spells or abilities.)",
  "number" : "285",
  "power" : "3",
  "toughness" : "1",
  "imageUrl" : "http://gatherer.wizards.com/Handlers/Image.ashx?multiverseid=130526&type=card",
  "id" : 3013
}, {
  "name" : "Troll Ascetic",
  "names" : null,
  "manaCost" : "{1}{G}{G}",
  "colors" : [ "G" ],
  "colorIdentity" : [ "G" ],
  "type" : "Creature — Troll Shaman",
  "supertypes" : null,
  "types" : [ "Creature" ],
  "subtypes" : [ "Troll", "Shaman" ],
  "rarity" : "Rare",
  "text" : "Hexproof (This creature can't be the target of spells or abilities your opponents control.)\n{1}{G}: Regenerate Troll Ascetic.",
  "number" : "305★",
  "power" : "3",
  "toughness" : "2",
  "imageUrl" : null,
  "id" : 3014
}, {
  "name" : "Giant Spider",
  "names" : null,
  "manaCost" : "{3}{G}",
  "colors" : [ "G" ],
  "colorIdentity" : [ "G" ],
  "type" : "Creature — Spider",
  "supertypes" : null,
  "types" : [ "Creature" ],
  "subtypes" : [ "Spider" ],
  "rarity" : "Common",
  "text" : "Reach (This creature can block creatures with flying.)",
  "number" : "267",
  "power" : "2",
  "toughness" : "4",
  "imageUrl" : "http://gatherer.wizards.com/Handlers/Image.ashx?multiverseid=129570&type=card",
  "id" : 3015
}, {
  "name" : "Commune with Nature",
  "names" : null,
  "manaCost" : "{G}",
  "colors" : [ "G" ],
  "colorIdentity" : [ "G" ],
  "type" : "Sorcery",
  "supertypes" : null,
  "types" : [ "Sorcery" ],
  "subtypes" : null,
  "rarity" : "Common",
  "text" : "Look at the top five cards of your library. You may reveal a creature card from among them and put it into your hand. Put the rest on the bottom of your library in any order.",
  "number" : "256",
  "power" : null,
  "toughness" : null,
  "imageUrl" : "http://gatherer.wizards.com/Handlers/Image.ashx?multiverseid=130521&type=card",
  "id" : 3016
}, {
  "name" : "Giant Spider",
  "names" : null,
  "manaCost" : "{3}{G}",
  "colors" : [ "G" ],
  "colorIdentity" : [ "G" ],
  "type" : "Creature — Spider",
  "supertypes" : null,
  "types" : [ "Creature" ],
  "subtypes" : [ "Spider" ],
  "rarity" : "Common",
  "text" : "Reach (This creature can block creatures with flying.)",
  "number" : "267★",
  "power" : "2",
  "toughness" : "4",
  "imageUrl" : null,
  "id" : 3017
}, {
  "name" : "Elvish Champion",
  "names" : null,
  "manaCost" : "{1}{G}{G}",
  "colors" : [ "G" ],
  "colorIdentity" : [ "G" ],
  "type" : "Creature — Elf",
  "supertypes" : null,
  "types" : [ "Creature" ],
  "subtypes" : [ "Elf" ],
  "rarity" : "Rare",
  "text" : "Other Elf creatures get +1/+1 and have forestwalk. (They can't be blocked as long as defending player controls a Forest.)",
  "number" : "261",
  "power" : "2",
  "toughness" : "2",
  "imageUrl" : "http://gatherer.wizards.com/Handlers/Image.ashx?multiverseid=129534&type=card",
  "id" : 3018
}, {
  "name" : "Femeref Archers",
  "names" : null,
  "manaCost" : "{2}{G}",
  "colors" : [ "G" ],
  "colorIdentity" : [ "G" ],
  "type" : "Creature — Human Archer",
  "supertypes" : null,
  "types" : [ "Creature" ],
  "subtypes" : [ "Human", "Archer" ],
  "rarity" : "Uncommon",
  "text" : "{T}: Femeref Archers deals 4 damage to target attacking creature with flying.",
  "number" : "264",
  "power" : "2",
  "toughness" : "2",
  "imageUrl" : "http://gatherer.wizards.com/Handlers/Image.ashx?multiverseid=135186&type=card",
  "id" : 3019
}, {
  "name" : "Spined Wurm",
  "names" : null,
  "manaCost" : "{4}{G}",
  "colors" : [ "G" ],
  "colorIdentity" : [ "G" ],
  "type" : "Creature — Wurm",
  "supertypes" : null,
  "types" : [ "Creature" ],
  "subtypes" : [ "Wurm" ],
  "rarity" : "Common",
  "text" : null,
  "number" : "298",
  "power" : "5",
  "toughness" : "4",
  "imageUrl" : "http://gatherer.wizards.com/Handlers/Image.ashx?multiverseid=129742&type=card",
  "id" : 3020
}, {
  "name" : "Birds of Paradise",
  "names" : null,
  "manaCost" : "{G}",
  "colors" : [ "G" ],
  "colorIdentity" : [ "G" ],
  "type" : "Creature — Bird",
  "supertypes" : null,
  "types" : [ "Creature" ],
  "subtypes" : [ "Bird" ],
  "rarity" : "Rare",
  "text" : "Flying\n{T}: Add one mana of any color.",
  "number" : "252",
  "power" : "0",
  "toughness" : "1",
  "imageUrl" : "http://gatherer.wizards.com/Handlers/Image.ashx?multiverseid=129906&type=card",
  "id" : 3021
}, {
  "name" : "Treetop Bracers",
  "names" : null,
  "manaCost" : "{1}{G}",
  "colors" : [ "G" ],
  "colorIdentity" : [ "G" ],
  "type" : "Enchantment — Aura",
  "supertypes" : null,
  "types" : [ "Enchantment" ],
  "subtypes" : [ "Aura" ],
  "rarity" : "Common",
  "text" : "Enchant creature (Target a creature as you cast this. This card enters the battlefield attached to that creature.)\nEnchanted creature gets +1/+1 and can't be blocked except by creatures with flying.",
  "number" : "304★",
  "power" : null,
  "toughness" : null,
  "imageUrl" : null,
  "id" : 3022
}, {
  "name" : "Abundance",
  "names" : null,
  "manaCost" : "{2}{G}{G}",
  "colors" : [ "G" ],
  "colorIdentity" : [ "G" ],
  "type" : "Enchantment",
  "supertypes" : null,
  "types" : [ "Enchantment" ],
  "subtypes" : null,
  "rarity" : "Rare",
  "text" : "If you would draw a card, you may instead choose land or nonland and reveal cards from the top of your library until you reveal a card of the chosen kind. Put that card into your hand and put all other cards revealed this way on the bottom of your library in any order.",
  "number" : "249",
  "power" : null,
  "toughness" : null,
  "imageUrl" : "http://gatherer.wizards.com/Handlers/Image.ashx?multiverseid=130483&type=card",
  "id" : 3023
}, {
  "name" : "Lure",
  "names" : null,
  "manaCost" : "{1}{G}{G}",
  "colors" : [ "G" ],
  "colorIdentity" : [ "G" ],
  "type" : "Enchantment — Aura",
  "supertypes" : null,
  "types" : [ "Enchantment" ],
  "subtypes" : [ "Aura" ],
  "rarity" : "Uncommon",
  "text" : "Enchant creature\nAll creatures able to block enchanted creature do so.",
  "number" : "276",
  "power" : null,
  "toughness" : null,
  "imageUrl" : "http://gatherer.wizards.com/Handlers/Image.ashx?multiverseid=135226&type=card",
  "id" : 3024
}, {
  "name" : "Treetop Village",
  "names" : null,
  "manaCost" : null,
  "colors" : null,
  "colorIdentity" : [ "G" ],
  "type" : "Land",
  "supertypes" : null,
  "types" : [ "Land" ],
  "subtypes" : null,
  "rarity" : "Uncommon",
  "text" : "Treetop Village enters the battlefield tapped.\n{T}: Add {G}.\n{1}{G}: Treetop Village becomes a 3/3 green Ape creature with trample until end of turn. It's still a land. (It can deal excess combat damage to the player or planeswalker it's attacking.)",
  "number" : "361★",
  "power" : null,
  "toughness" : null,
  "imageUrl" : null,
  "id" : 3025
}, {
  "name" : "Wall of Wood",
  "names" : null,
  "manaCost" : "{G}",
  "colors" : [ "G" ],
  "colorIdentity" : [ "G" ],
  "type" : "Creature — Wall",
  "supertypes" : null,
  "types" : [ "Creature" ],
  "subtypes" : [ "Wall" ],
  "rarity" : "Common",
  "text" : "Defender (This creature can't attack.)",
  "number" : "309★",
  "power" : "0",
  "toughness" : "3",
  "imageUrl" : null,
  "id" : 3026
}, {
  "name" : "Enormous Baloth",
  "names" : null,
  "manaCost" : "{6}{G}",
  "colors" : [ "G" ],
  "colorIdentity" : [ "G" ],
  "type" : "Creature — Beast",
  "supertypes" : null,
  "types" : [ "Creature" ],
  "subtypes" : [ "Beast" ],
  "rarity" : "Uncommon",
  "text" : null,
  "number" : "263",
  "power" : "7",
  "toughness" : "7",
  "imageUrl" : "http://gatherer.wizards.com/Handlers/Image.ashx?multiverseid=135263&type=card",
  "id" : 3027
}, {
  "name" : "Avatar of Might",
  "names" : null,
  "manaCost" : "{6}{G}{G}",
  "colors" : [ "G" ],
  "colorIdentity" : [ "G" ],
  "type" : "Creature — Avatar",
  "supertypes" : null,
  "types" : [ "Creature" ],
  "subtypes" : [ "Avatar" ],
  "rarity" : "Rare",
  "text" : "If an opponent controls at least four more creatures than you, this spell costs {6} less to cast.\nTrample (This creature can deal excess combat damage to the player or planeswalker it's attacking.)",
  "number" : "251★",
  "power" : "8",
  "toughness" : "8",
  "imageUrl" : null,
  "id" : 3028
}, {
  "name" : "Naturalize",
  "names" : null,
  "manaCost" : "{1}{G}",
  "colors" : [ "G" ],
  "colorIdentity" : [ "G" ],
  "type" : "Instant",
  "supertypes" : null,
  "types" : [ "Instant" ],
  "subtypes" : null,
  "rarity" : "Common",
  "text" : "Destroy target artifact or enchantment.",
  "number" : "282",
  "power" : null,
  "toughness" : null,
  "imageUrl" : "http://gatherer.wizards.com/Handlers/Image.ashx?multiverseid=129656&type=card",
  "id" : 3029
}, {
  "name" : "Rushwood Dryad",
  "names" : null,
  "manaCost" : "{1}{G}",
  "colors" : [ "G" ],
  "colorIdentity" : [ "G" ],
  "type" : "Creature — Dryad",
  "supertypes" : null,
  "types" : [ "Creature" ],
  "subtypes" : [ "Dryad" ],
  "rarity" : "Common",
  "text" : "Forestwalk (This creature can't be blocked as long as defending player controls a Forest.)",
  "number" : "294",
  "power" : "2",
  "toughness" : "1",
  "imageUrl" : "http://gatherer.wizards.com/Handlers/Image.ashx?multiverseid=136285&type=card",
  "id" : 3030
}, {
  "name" : "Overrun",
  "names" : null,
  "manaCost" : "{2}{G}{G}{G}",
  "colors" : [ "G" ],
  "colorIdentity" : [ "G" ],
  "type" : "Sorcery",
  "supertypes" : null,
  "types" : [ "Sorcery" ],
  "subtypes" : null,
  "rarity" : "Uncommon",
  "text" : "Creatures you control get +3/+3 and gain trample until end of turn.",
  "number" : "284★",
  "power" : null,
  "toughness" : null,
  "imageUrl" : null,
  "id" : 3031
}, {
  "name" : "Troll Ascetic",
  "names" : null,
  "manaCost" : "{1}{G}{G}",
  "colors" : [ "G" ],
  "colorIdentity" : [ "G" ],
  "type" : "Creature — Troll Shaman",
  "supertypes" : null,
  "types" : [ "Creature" ],
  "subtypes" : [ "Troll", "Shaman" ],
  "rarity" : "Rare",
  "text" : "Hexproof (This creature can't be the target of spells or abilities your opponents control.)\n{1}{G}: Regenerate Troll Ascetic.",
  "number" : "305",
  "power" : "3",
  "toughness" : "2",
  "imageUrl" : "http://gatherer.wizards.com/Handlers/Image.ashx?multiverseid=130498&type=card",
  "id" : 3032
}, {
  "name" : "Civic Wayfinder",
  "names" : null,
  "manaCost" : "{2}{G}",
  "colors" : [ "G" ],
  "colorIdentity" : [ "G" ],
  "type" : "Creature — Elf Druid Warrior",
  "supertypes" : null,
  "types" : [ "Creature" ],
  "subtypes" : [ "Elf", "Druid", "Warrior" ],
  "rarity" : "Common",
  "text" : "When Civic Wayfinder enters the battlefield, you may search your library for a basic land card, reveal it, put it into your hand, then shuffle.",
  "number" : "255",
  "power" : "2",
  "toughness" : "2",
  "imageUrl" : "http://gatherer.wizards.com/Handlers/Image.ashx?multiverseid=130522&type=card",
  "id" : 3033
}, {
  "name" : "Kavu Climber",
  "names" : null,
  "manaCost" : "{3}{G}{G}",
  "colors" : [ "G" ],
  "colorIdentity" : [ "G" ],
  "type" : "Creature — Kavu",
  "supertypes" : null,
  "types" : [ "Creature" ],
  "subtypes" : [ "Kavu" ],
  "rarity" : "Common",
  "text" : "When Kavu Climber enters the battlefield, draw a card.",
  "number" : "273",
  "power" : "3",
  "toughness" : "3",
  "imageUrl" : "http://gatherer.wizards.com/Handlers/Image.ashx?multiverseid=129511&type=card",
  "id" : 3034
}, {
  "name" : "Treetop Village",
  "names" : null,
  "manaCost" : null,
  "colors" : null,
  "colorIdentity" : [ "G" ],
  "type" : "Land",
  "supertypes" : null,
  "types" : [ "Land" ],
  "subtypes" : null,
  "rarity" : "Uncommon",
  "text" : "Treetop Village enters the battlefield tapped.\n{T}: Add {G}.\n{1}{G}: Treetop Village becomes a 3/3 green Ape creature with trample until end of turn. It's still a land. (It can deal excess combat damage to the player or planeswalker it's attacking.)",
  "number" : "361",
  "power" : null,
  "toughness" : null,
  "imageUrl" : "http://gatherer.wizards.com/Handlers/Image.ashx?multiverseid=106455&type=card",
  "id" : 3035
}, {
  "name" : "Hunted Wumpus",
  "names" : null,
  "manaCost" : "{3}{G}",
  "colors" : [ "G" ],
  "colorIdentity" : [ "G" ],
  "type" : "Creature — Beast",
  "supertypes" : null,
  "types" : [ "Creature" ],
  "subtypes" : [ "Beast" ],
  "rarity" : "Uncommon",
  "text" : "When Hunted Wumpus enters the battlefield, each other player may put a creature card from their hand onto the battlefield.",
  "number" : "269",
  "power" : "6",
  "toughness" : "6",
  "imageUrl" : "http://gatherer.wizards.com/Handlers/Image.ashx?multiverseid=129599&type=card",
  "id" : 3036
}, {
  "name" : "Elvish Piper",
  "names" : null,
  "manaCost" : "{3}{G}",
  "colors" : [ "G" ],
  "colorIdentity" : [ "G" ],
  "type" : "Creature — Elf Shaman",
  "supertypes" : null,
  "types" : [ "Creature" ],
  "subtypes" : [ "Elf", "Shaman" ],
  "rarity" : "Rare",
  "text" : "{G}, {T}: You may put a creature card from your hand onto the battlefield.",
  "number" : "262",
  "power" : "1",
  "toughness" : "1",
  "imageUrl" : "http://gatherer.wizards.com/Handlers/Image.ashx?multiverseid=129535&type=card",
  "id" : 3037
}, {
  "name" : "Legacy Weapon",
  "names" : null,
  "manaCost" : "{7}",
  "colors" : null,
  "colorIdentity" : [ "B", "G", "R", "U", "W" ],
  "type" : "Legendary Artifact",
  "supertypes" : [ "Legendary" ],
  "types" : [ "Artifact" ],
  "subtypes" : null,
  "rarity" : "Rare",
  "text" : "{W}{U}{B}{R}{G}: Exile target permanent.\nIf Legacy Weapon would be put into a graveyard from anywhere, reveal Legacy Weapon and shuffle it into its owner's library instead.",
  "number" : "330",
  "power" : null,
  "toughness" : null,
  "imageUrl" : "http://gatherer.wizards.com/Handlers/Image.ashx?multiverseid=135242&type=card",
  "id" : 3038
}, {
  "name" : "Craw Wurm",
  "names" : null,
  "manaCost" : "{4}{G}{G}",
  "colors" : [ "G" ],
  "colorIdentity" : [ "G" ],
  "type" : "Creature — Wurm",
  "supertypes" : null,
  "types" : [ "Creature" ],
  "subtypes" : [ "Wurm" ],
  "rarity" : "Common",
  "text" : null,
  "number" : "257",
  "power" : "6",
  "toughness" : "4",
  "imageUrl" : "http://gatherer.wizards.com/Handlers/Image.ashx?multiverseid=130527&type=card",
  "id" : 3039
}, {
  "name" : "Might of Oaks",
  "names" : null,
  "manaCost" : "{3}{G}",
  "colors" : [ "G" ],
  "colorIdentity" : [ "G" ],
  "type" : "Instant",
  "supertypes" : null,
  "types" : [ "Instant" ],
  "subtypes" : null,
  "rarity" : "Rare",
  "text" : "Target creature gets +7/+7 until end of turn.",
  "number" : "277",
  "power" : null,
  "toughness" : null,
  "imageUrl" : "http://gatherer.wizards.com/Handlers/Image.ashx?multiverseid=129642&type=card",
  "id" : 3040
}, {
  "name" : "Mirri, Cat Warrior",
  "names" : null,
  "manaCost" : "{1}{G}{G}",
  "colors" : [ "G" ],
  "colorIdentity" : [ "G" ],
  "type" : "Legendary Creature — Cat Warrior",
  "supertypes" : [ "Legendary" ],
  "types" : [ "Creature" ],
  "subtypes" : [ "Cat", "Warrior" ],
  "rarity" : "Rare",
  "text" : "First strike, forestwalk, vigilance (This creature deals combat damage before creatures without first strike, it can't be blocked as long as defending player controls a Forest, and attacking doesn't cause this creature to tap.)",
  "number" : "279★",
  "power" : "2",
  "toughness" : "3",
  "imageUrl" : null,
  "id" : 3041
}, {
  "name" : "Might Weaver",
  "names" : null,
  "manaCost" : "{1}{G}",
  "colors" : [ "G" ],
  "colorIdentity" : [ "G" ],
  "type" : "Creature — Human Wizard",
  "supertypes" : null,
  "types" : [ "Creature" ],
  "subtypes" : [ "Human", "Wizard" ],
  "rarity" : "Uncommon",
  "text" : "{2}: Target red or white creature gains trample until end of turn. (It can deal excess combat damage to the player or planeswalker it's attacking.)",
  "number" : "278★",
  "power" : "2",
  "toughness" : "1",
  "imageUrl" : null,
  "id" : 3042
}, {
  "name" : "Gaea's Herald",
  "names" : null,
  "manaCost" : "{1}{G}",
  "colors" : [ "G" ],
  "colorIdentity" : [ "G" ],
  "type" : "Creature — Elf",
  "supertypes" : null,
  "types" : [ "Creature" ],
  "subtypes" : [ "Elf" ],
  "rarity" : "Rare",
  "text" : "Creature spells can't be countered.",
  "number" : "265",
  "power" : "1",
  "toughness" : "1",
  "imageUrl" : "http://gatherer.wizards.com/Handlers/Image.ashx?multiverseid=129789&type=card",
  "id" : 3043
}, {
  "name" : "Berserk",
  "names" : null,
  "manaCost" : "{G}",
  "colors" : [ "G" ],
  "colorIdentity" : [ "G" ],
  "type" : "Instant",
  "supertypes" : null,
  "types" : [ "Instant" ],
  "subtypes" : null,
  "rarity" : "Uncommon",
  "text" : "Cast this spell only before the combat damage step.\nTarget creature gains trample and gets +X/+0 until end of turn, where X is its power. At the beginning of the next end step, destroy that creature if it attacked this turn.",
  "number" : "186",
  "power" : null,
  "toughness" : null,
  "imageUrl" : "http://gatherer.wizards.com/Handlers/Image.ashx?multiverseid=738&type=card",
  "id" : 3044
}, {
  "name" : "Llanowar Wastes",
  "names" : null,
  "manaCost" : null,
  "colors" : null,
  "colorIdentity" : [ "B", "G" ],
  "type" : "Land",
  "supertypes" : null,
  "types" : [ "Land" ],
  "subtypes" : null,
  "rarity" : "Rare",
  "text" : "{T}: Add {C}.\n{T}: Add {B} or {G}. Llanowar Wastes deals 1 damage to you.",
  "number" : "355",
  "power" : null,
  "toughness" : null,
  "imageUrl" : "http://gatherer.wizards.com/Handlers/Image.ashx?multiverseid=129627&type=card",
  "id" : 3045
}, {
  "name" : "Scion of the Wild",
  "names" : null,
  "manaCost" : "{1}{G}{G}",
  "colors" : [ "G" ],
  "colorIdentity" : [ "G" ],
  "type" : "Creature — Avatar",
  "supertypes" : null,
  "types" : [ "Creature" ],
  "subtypes" : [ "Avatar" ],
  "rarity" : "Rare",
  "text" : "Scion of the Wild's power and toughness are each equal to the number of creatures you control.",
  "number" : "295",
  "power" : "*",
  "toughness" : "*",
  "imageUrl" : "http://gatherer.wizards.com/Handlers/Image.ashx?multiverseid=130504&type=card",
  "id" : 3046
}, {
  "name" : "Forest",
  "names" : null,
  "manaCost" : null,
  "colors" : null,
  "colorIdentity" : [ "G" ],
  "type" : "Basic Land — Forest",
  "supertypes" : [ "Basic" ],
  "types" : [ "Land" ],
  "subtypes" : [ "Forest" ],
  "rarity" : "Common",
  "text" : "({T}: Add {G}.)",
  "number" : "380",
  "power" : null,
  "toughness" : null,
  "imageUrl" : "http://gatherer.wizards.com/Handlers/Image.ashx?multiverseid=129559&type=card",
  "id" : 3047
}, {
  "name" : "Rhox",
  "names" : null,
  "manaCost" : "{4}{G}{G}",
  "colors" : [ "G" ],
  "colorIdentity" : [ "G" ],
  "type" : "Creature — Rhino Beast",
  "supertypes" : null,
  "types" : [ "Creature" ],
  "subtypes" : [ "Rhino", "Beast" ],
  "rarity" : "Rare",
  "text" : "You may have Rhox assign its combat damage as though it weren't blocked.\n{2}{G}: Regenerate Rhox. (The next time this creature would be destroyed this turn, it isn't. Instead tap it, remove all damage from it, and remove it from combat.)",
  "number" : "291★",
  "power" : "5",
  "toughness" : "5",
  "imageUrl" : null,
  "id" : 3048
}, {
  "name" : "Yavimaya Coast",
  "names" : null,
  "manaCost" : null,
  "colors" : null,
  "colorIdentity" : [ "G", "U" ],
  "type" : "Land",
  "supertypes" : null,
  "types" : [ "Land" ],
  "subtypes" : null,
  "rarity" : "Rare",
  "text" : "{T}: Add {C}.\n{T}: Add {G} or {U}. Yavimaya Coast deals 1 damage to you.",
  "number" : "363",
  "power" : null,
  "toughness" : null,
  "imageUrl" : "http://gatherer.wizards.com/Handlers/Image.ashx?multiverseid=129810&type=card",
  "id" : 3049
}, {
  "name" : "Seedborn Muse",
  "names" : null,
  "manaCost" : "{3}{G}{G}",
  "colors" : [ "G" ],
  "colorIdentity" : [ "G" ],
  "type" : "Creature — Spirit",
  "supertypes" : null,
  "types" : [ "Creature" ],
  "subtypes" : [ "Spirit" ],
  "rarity" : "Rare",
  "text" : "Untap all permanents you control during each other player's untap step.",
  "number" : "296",
  "power" : "2",
  "toughness" : "4",
  "imageUrl" : "http://gatherer.wizards.com/Handlers/Image.ashx?multiverseid=129722&type=card",
  "id" : 3050
}, {
  "name" : "Overgrowth",
  "names" : null,
  "manaCost" : "{2}{G}",
  "colors" : [ "G" ],
  "colorIdentity" : [ "G" ],
  "type" : "Enchantment — Aura",
  "supertypes" : null,
  "types" : [ "Enchantment" ],
  "subtypes" : [ "Aura" ],
  "rarity" : "Common",
  "text" : "Enchant land\nWhenever enchanted land is tapped for mana, its controller adds an additional {G}{G}.",
  "number" : "283",
  "power" : null,
  "toughness" : null,
  "imageUrl" : "http://gatherer.wizards.com/Handlers/Image.ashx?multiverseid=135282&type=card",
  "id" : 3051
} ]